{
  "metadata": {
    "Entity": "biomass",
    "Description": "Biomass refers to organic matter, such as plants or plant-based materials, that can be used as a renewable energy source.",
    "Category": "Technology",
    "Tags": [
      "Renewable Energy",
      "Organic Matter"
    ],
    "Dimension": "Technology",
    "Acronym": null,
    "Importance": 3.0,
    "Synonyms": null
  },
  "knowledge graph": {
    "entities": [
      "offshore renewable energy",
      "research and development",
      "agricultural sector",
      "just energy transition",
      "energy efficiency",
      "sustainable development goals",
      "climate change mitigation",
      "energy and modernization"
    ],
    "relations": {
      "level 1": [
        {
          "Relation": "implements",
          "Object": "energy and modernization",
          "Description": "Biomass implements energy generation methods that utilize organic materials to produce heat, electricity, or biofuels.",
          "Importance": 4
        },
        {
          "Relation": "funds",
          "Object": "research and development",
          "Description": "Biomass funds research and development initiatives to improve the efficiency and sustainability of biomass energy technologies.",
          "Importance": 3
        },
        {
          "Relation": "focuses_on",
          "Object": "offshore renewable energy",
          "Description": "Biomass focuses on renewable energy sources by utilizing organic materials to generate heat, electricity, or biofuels.",
          "Importance": 4
        },
        {
          "Relation": "in",
          "Object": "just energy transition",
          "Description": "Biomass plays a role in the energy transition by providing a renewable alternative to fossil fuels for heat and electricity generation.",
          "Importance": 3
        },
        {
          "Relation": "partners_with",
          "Object": "agricultural sector",
          "Description": "Biomass partners with the agricultural sector to obtain organic materials for biomass energy production.",
          "Importance": 2
        },
        {
          "Relation": "contributes_to",
          "Object": "climate change mitigation",
          "Description": "Biomass contributes to climate change mitigation by reducing greenhouse gas emissions through the use of renewable energy sources.",
          "Importance": 4
        },
        {
          "Relation": "monitors",
          "Object": "energy efficiency",
          "Description": "Biomass monitors energy efficiency in biomass energy production processes to optimize resource utilization and minimize waste.",
          "Importance": 3
        },
        {
          "Relation": "targets",
          "Object": "sustainable development goals",
          "Description": "Biomass targets sustainable development goals by contributing to affordable and clean energy access for all.",
          "Importance": 4
        }
      ],
      "level 2": [
        {
          "Subject": "energy and modernization",
          "Relation": "implements",
          "Object": "building standards",
          "Description": "Energy and modernization implements rigorous building standards that promote the use of energy-saving designs and materials.",
          "Importance": 4
        },
        {
          "Subject": "energy and modernization",
          "Relation": "funds",
          "Object": "renewable energy agencies",
          "Description": "Energy and modernization funds renewable energy projects to support the transition to clean and sustainable energy sources.",
          "Importance": 3
        },
        {
          "Subject": "offshore renewable energy",
          "Relation": "implements",
          "Object": "building standards",
          "Description": "Offshore renewable energy implements building standards that promote the use of sustainable energy sources and technologies.",
          "Importance": 4
        },
        {
          "Subject": "offshore renewable energy",
          "Relation": "funds",
          "Object": "research and development",
          "Description": "Offshore renewable energy funds research and development projects to advance the use of sustainable energy technologies.",
          "Importance": 3
        },
        {
          "Subject": "just energy transition",
          "Relation": "collaborates_with",
          "Object": "local communities",
          "Description": "The just energy transition collaborates with local communities to ensure a fair and inclusive transition to sustainable energy.",
          "Importance": 4
        },
        {
          "Subject": "just energy transition",
          "Relation": "supports",
          "Object": "energy equity",
          "Description": "The just energy transition supports energy equity by promoting equal access to clean and affordable energy.",
          "Importance": 4
        },
        {
          "Subject": "energy efficiency",
          "Relation": "addresses",
          "Object": "energy storage",
          "Description": "Energy efficiency measures address energy waste by promoting the use of energy-efficient technologies and practices.",
          "Importance": 4
        },
        {
          "Subject": "energy efficiency",
          "Relation": "collaborates_with",
          "Object": "industries",
          "Description": "Energy efficiency collaborates with industries to develop and implement energy-saving measures and technologies.",
          "Importance": 4
        }
      ],
      "level 3": [
        {
          "Subject": "renewable energy agencies",
          "Relation": "employs",
          "Object": "renewable energy agencies",
          "Description": "Renewable energy agencies employ experts in the field of renewable energy to drive innovation and promote the adoption of clean energy technologies.",
          "Importance": 4
        },
        {
          "Subject": "energy markets",
          "Relation": "addresses",
          "Object": "energy markets",
          "Description": "Energy markets address the issue of energy access by ensuring the availability and affordability of energy sources for all segments of society.",
          "Importance": 4
        },
        {
          "Subject": "just energy transition",
          "Relation": "employs",
          "Object": "renewable energy certificates",
          "Description": "The just energy transition employs a renewable energy workforce to support the transition to clean energy sources.",
          "Importance": 3
        },
        {
          "Subject": "energy poverty indices",
          "Relation": "implements",
          "Object": "energy access programs",
          "Description": "Energy poverty indices implement energy access programs to provide affordable and reliable energy services to underserved communities.",
          "Importance": 4
        }
      ]
    },
    "sub-elements": [
      "wood biomass",
      "agricultural biomass",
      "animal biomass",
      "aquatic biomass",
      "municipal solid waste biomass"
    ],
    "subelement_relations": [
      {
        "Sub-element": "wood biomass",
        "Relation": "is a sub-element of",
        "Parent": "biomass",
        "Description": "Wood biomass refers to the use of wood and wood products as a source of energy. It can be derived from forest residues, logging residues, and wood processing waste. Wood biomass is a renewable and carbon-neutral source of energy.",
        "Importance": 4
      },
      {
        "Sub-element": "agricultural biomass",
        "Relation": "is a sub-element of",
        "Parent": "biomass",
        "Description": "Agricultural biomass includes crop residues, such as stalks, husks, and straw, as well as dedicated energy crops grown specifically for energy production. It is a sustainable source of energy that can reduce greenhouse gas emissions and promote rural development.",
        "Importance": 3
      },
      {
        "Sub-element": "animal biomass",
        "Relation": "is a sub-element of",
        "Parent": "biomass",
        "Description": "Animal biomass refers to the use of animal waste, such as manure and carcasses, as a source of energy. It can be converted into biogas through anaerobic digestion, providing a renewable and environmentally friendly energy option.",
        "Importance": 3
      },
      {
        "Sub-element": "aquatic biomass",
        "Relation": "is a sub-element of",
        "Parent": "biomass",
        "Description": "Aquatic biomass includes algae and aquatic plants that can be used as a source of energy. It can be converted into biofuels, such as biodiesel and bioethanol, through various processes. Aquatic biomass has the potential to provide a sustainable and carbon-neutral energy solution.",
        "Importance": 2
      },
      {
        "Sub-element": "municipal solid waste biomass",
        "Relation": "is a sub-element of",
        "Parent": "biomass",
        "Description": "Municipal solid waste biomass refers to the use of organic waste from households and businesses as a source of energy. It can be converted into biogas or used for the production of heat and electricity through incineration. Utilizing municipal solid waste biomass can help reduce landfill waste and promote a circular economy.",
        "Importance": 3
      }
    ]
  }
}