{
    "metadata": {},
    "knowledge graph": {
        "entities": [],
        "relations": {
            "Medical Devices": [
                {
                    "Relation": "RELATIONSHIP",
                    "Object": "ENTITY2",
                    "Strength": "7",
                    "Description": "CONTENT DESCRIPTION"
                },
                {
                    "Relation": "RELATIONSHIP",
                    "Object": "ENTITY3",
                    "Strength": "5",
                    "Description": "CONTENT DESCRIPTION"
                },
                {
                    "Relation": "RELATIONSHIP",
                    "Object": "ENTITY4",
                    "Strength": "9",
                    "Description": "CONTENT DESCRIPTION"
                },
                {
                    "Relation": "RELATIONSHIP",
                    "Object": "ENTITY5",
                    "Strength": "6",
                    "Description": "CONTENT DESCRIPTION"
                }
            ]
        }
    }
}