{
    "metadata": {},
    "knowledge graph": {
        "entities": [],
        "relations": {
            "Cooling tower": [
                {
                    "Relation": "Provides cooling",
                    "Object": "Water pump",
                    "Strength": "8",
                    "Description": "The cooling tower provides cooled water to the water pump for circulation."
                },
                {
                    "Relation": "Receives hot water",
                    "Object": "Chiller",
                    "Strength": "9",
                    "Description": "The cooling tower receives hot water from the chiller to cool it down."
                },
                {
                    "Relation": "Exchanges heat",
                    "Object": "Heat exchanger",
                    "Strength": "7",
                    "Description": "The cooling tower exchanges heat with the heat exchanger to cool down the fluid."
                },
                {
                    "Relation": "Receives hot vapor",
                    "Object": "Condenser",
                    "Strength": "6",
                    "Description": "The cooling tower receives hot vapor from the condenser and cools it down to convert it back into a liquid."
                }
            ]
        }
    }
}